Metadata-Version: 1.0
Name: mbfirstpackage
Version: 0.1
Summary: My Gaussian and binomial distributions
Home-page: UNKNOWN
Author: UNKNOWN
Author-email: UNKNOWN
License: UNKNOWN
Platform: UNKNOWN
